{
  "banks": [
    {
      "Sr_No": 1,
      "Bank_Name": "ALLAHABAD BANK",
      "Infrastructure": {
        "ATMs_CRMs": {
          "On_site": 460,
          "Off_site": 332
        },
        "PoS": 233,
        "Micro_ATMs": 0,
        "Bharat_QR_Codes": 0,
        "UPI_QR_Codes": 0,
        "Credit_Cards": 0,
        "Debit_Cards": 2531314
      },
      "Card_Payments_Transactions": {
        "Credit_Card": {
          "at_PoS": {
            "Volume": 0,
            "Value": 0
          },
          "Online_ecom": {
            "Volume": 0,
            "Value": 0
          },
          "Others": {
            "Volume": 0,
            "Value": 0
          },
          "Cash_Withdrawal": {
            "At_ATM": {
              "Volume": 0,
              "Value": 0
            }
          }
        },
        "Debit_Card": {
          "at_PoS": {
            "Volume": 117480,
            "Value": 263.6
          },
          "Online_ecom": {
            "Volume": 0,
            "Value": 0
          },
          "Others": {
            "Volume": 0,
            "Value": 0
          },
          "Cash_Withdrawal": {
            "At_ATM": {
              "Volume": 3237077,
              "Value": 9301.6
            },
            "At_PoS": {
              "Volume": 0,
              "Value": 0
            }
          }
        }
      },
      "Bank_Short_Name": "Allahabad",
      "Bank_Type": "Public Sector Banks"
    },
    {
      "Sr_No": 2,
      "Bank_Name": "ANDHRA BANK",
      "Infrastructure": {
        "ATMs_CRMs": {
          "On_site": 858,
          "Off_site": 619
        },
        "PoS": 2369,
        "Micro_ATMs": 0,
        "Bharat_QR_Codes": 0,
        "UPI_QR_Codes": 0,
        "Credit_Cards": 130597,
        "Debit_Cards": 9249591
      },
      "Card_Payments_Transactions": {
        "Credit_Card": {
          "at_PoS": {
            "Volume": 156001,
            "Value": 399.5
          },
          "Online_ecom": {
            "Volume": 0,
            "Value": 0
          },
          "Others": {
            "Volume": 0,
            "Value": 0
          },
          "Cash_Withdrawal": {
            "At_ATM": {
              "Volume": 9445,
              "Value": 40.8
            }
          }
        },
        "Debit_Card": {
          "at_PoS": {
            "Volume": 656622,
            "Value": 838.5
          },
          "Online_ecom": {
            "Volume": 0,
            "Value": 0
          },
          "Others": {
            "Volume": 0,
            "Value": 0
          },
          "Cash_Withdrawal": {
            "At_ATM": {
              "Volume": 10361335,
              "Value": 18988.5
            },
            "At_PoS": {
              "Volume": 0,
              "Value": 0
            }
          }
        }
      },
      "Bank_Short_Name": "ANDHRA",
      "Bank_Type": "Public Sector Banks"
    },
    {
      "Sr_No": 3,
      "Bank_Name": "BANK OF BARODA",
      "Infrastructure": {
        "ATMs_CRMs": {
          "On_site": 3294,
          "Off_site": 1569
        },
        "PoS": 7584,
        "Micro_ATMs": 0,
        "Bharat_QR_Codes": 0,
        "UPI_QR_Codes": 0,
        "Credit_Cards": 71063,
        "Debit_Cards": 12465979
      },
      "Card_Payments_Transactions": {
        "Credit_Card": {
          "at_PoS": {
            "Volume": 101873,
            "Value": 255.2
          },
          "Online_ecom": {
            "Volume": 0,
            "Value": 0
          },
          "Others": {
            "Volume": 0,
            "Value": 0
          },
          "Cash_Withdrawal": {
            "At_ATM": {
              "Volume": 1323,
              "Value": 4.5
            }
          }
        },
        "Debit_Card": {
          "at_PoS": {
            "Volume": 1161613,
            "Value": 1534.1
          },
          "Online_ecom": {
            "Volume": 0,
            "Value": 0
          },
          "Others": {
            "Volume": 0,
            "Value": 0
          },
          "Cash_Withdrawal": {
            "At_ATM": {
              "Volume": 10224683,
              "Value": 41966.8
            },
            "At_PoS": {
              "Volume": 0,
              "Value": 0
            }
          }
        }
      },
      "Bank_Short_Name": "BOB",
      "Bank_Type": "Public Sector Banks"
    },
    {
      "Sr_No": 4,
      "Bank_Name": "BANK OF INDIA",
      "Infrastructure": {
        "ATMs_CRMs": {
          "On_site": 1688,
          "Off_site": 1526
        },
        "PoS": 2565,
        "Micro_ATMs": 0,
        "Bharat_QR_Codes": 0,
        "UPI_QR_Codes": 0,
        "Credit_Cards": 122841,
        "Debit_Cards": 15833596
      },
      "Card_Payments_Transactions": {
        "Credit_Card": {
          "at_PoS": {
            "Volume": 112022,
            "Value": 299.3
          },
          "Online_ecom": {
            "Volume": 0,
            "Value": 0
          },
          "Others": {
            "Volume": 0,
            "Value": 0
          },
          "Cash_Withdrawal": {
            "At_ATM": {
              "Volume": 8364,
              "Value": 54.6
            }
          }
        },
        "Debit_Card": {
          "at_PoS": {
            "Volume": 1306316,
            "Value": 1547.7
          },
          "Online_ecom": {
            "Volume": 0,
            "Value": 0
          },
          "Others": {
            "Volume": 0,
            "Value": 0
          },
          "Cash_Withdrawal": {
            "At_ATM": {
              "Volume": 13854347,
              "Value": 34193.7
            },
            "At_PoS": {
              "Volume": 0,
              "Value": 0
            }
          }
        }
      },
      "Bank_Short_Name": "BOI",
      "Bank_Type": "Public Sector Banks"
    },
    {
      "Sr_No": 5,
      "Bank_Name": "BANK OF MAHARASHTRA",
      "Infrastructure": {
        "ATMs_CRMs": {
          "On_site": 641,
          "Off_site": 345
        },
        "PoS": 23,
        "Micro_ATMs": 0,
        "Bharat_QR_Codes": 0,
        "UPI_QR_Codes": 0,
        "Credit_Cards": 23237,
        "Debit_Cards": 4085692
      },
      "Card_Payments_Transactions": {
        "Credit_Card": {
          "at_PoS": {
            "Volume": 35356,
            "Value": 85.91738361
          },
          "Online_ecom": {
            "Volume": 0,
            "Value": 0
          },
          "Others": {
            "Volume": 0,
            "Value": 0
          },
          "Cash_Withdrawal": {
            "At_ATM": {
              "Volume": 237,
              "Value": 0.77129455
            }
          }
        },
        "Debit_Card": {
          "at_PoS": {
            "Volume": 441502,
            "Value": 577.82689591
          },
          "Online_ecom": {
            "Volume": 0,
            "Value": 0
          },
          "Others": {
            "Volume": 0,
            "Value": 0
          },
          "Cash_Withdrawal": {
            "At_ATM": {
              "Volume": 3459188,
              "Value": 9057.1894
            },
            "At_PoS": {
              "Volume": 0,
              "Value": 0
            }
          }
        }
      },
      "Bank_Short_Name": "BOM",
      "Bank_Type": "Public Sector Banks"
    },
    {
      "Sr_No": 6,
      "Bank_Name": "CANARA BANK",
      "Infrastructure": {
        "ATMs_CRMs": {
          "On_site": 2326,
          "Off_site": 2039
        },
        "PoS": 1021,
        "Micro_ATMs": 0,
        "Bharat_QR_Codes": 0,
        "UPI_QR_Codes": 0,
        "Credit_Cards": 63586,
        "Debit_Cards": 12532498
      },
      "Card_Payments_Transactions": {
        "Credit_Card": {
          "at_PoS": {
            "Volume": 63448,
            "Value": 177.39999999999998
          },
          "Online_ecom": {
            "Volume": 0,
            "Value": 0
          },
          "Others": {
            "Volume": 0,
            "Value": 0
          },
          "Cash_Withdrawal": {
            "At_ATM": {
              "Volume": 10436,
              "Value": 49.5
            }
          }
        },
        "Debit_Card": {
          "at_PoS": {
            "Volume": 794133,
            "Value": 1319.1
          },
          "Online_ecom": {
            "Volume": 0,
            "Value": 0
          },
          "Others": {
            "Volume": 0,
            "Value": 0
          },
          "Cash_Withdrawal": {
            "At_ATM": {
              "Volume": 13097261,
              "Value": 36792.2
            },
            "At_PoS": {
              "Volume": 0,
              "Value": 0
            }
          }
        }
      },
      "Bank_Short_Name": "CANARA",
      "Bank_Type": "Public Sector Banks"
    },
    {
      "Sr_No": 7,
      "Bank_Name": "CENTRAL BANK OF INDIA",
      "Infrastructure": {
        "ATMs_CRMs": {
          "On_site": 1834,
          "Off_site": 1469
        },
        "PoS": 1315,
        "Micro_ATMs": 0,
        "Bharat_QR_Codes": 0,
        "UPI_QR_Codes": 0,
        "Credit_Cards": 58921,
        "Debit_Cards": 6090916
      },
      "Card_Payments_Transactions": {
        "Credit_Card": {
          "at_PoS": {
            "Volume": 56974,
            "Value": 279.40000000000003
          },
          "Online_ecom": {
            "Volume": 0,
            "Value": 0
          },
          "Others": {
            "Volume": 0,
            "Value": 0
          },
          "Cash_Withdrawal": {
            "At_ATM": {
              "Volume": 294,
              "Value": 1.1
            }
          }
        },
        "Debit_Card": {
          "at_PoS": {
            "Volume": 276011,
            "Value": 606.1
          },
          "Online_ecom": {
            "Volume": 0,
            "Value": 0
          },
          "Others": {
            "Volume": 0,
            "Value": 0
          },
          "Cash_Withdrawal": {
            "At_ATM": {
              "Volume": 13437663,
              "Value": 46581.6
            },
            "At_PoS": {
              "Volume": 0,
              "Value": 0
            }
          }
        }
      },
      "Bank_Short_Name": "CBI",
      "Bank_Type": "Public Sector Banks"
    },
    {
      "Sr_No": 8,
      "Bank_Name": "CORPORATION BANK",
      "Infrastructure": {
        "ATMs_CRMs": {
          "On_site": 1109,
          "Off_site": 787
        },
        "PoS": 14072,
        "Micro_ATMs": 0,
        "Bharat_QR_Codes": 0,
        "UPI_QR_Codes": 0,
        "Credit_Cards": 78960,
        "Debit_Cards": 5584912
      },
      "Card_Payments_Transactions": {
        "Credit_Card": {
          "at_PoS": {
            "Volume": 62611,
            "Value": 153.9
          },
          "Online_ecom": {
            "Volume": 0,
            "Value": 0
          },
          "Others": {
            "Volume": 0,
            "Value": 0
          },
          "Cash_Withdrawal": {
            "At_ATM": {
              "Volume": 805,
              "Value": 3.5999999999999996
            }
          }
        },
        "Debit_Card": {
          "at_PoS": {
            "Volume": 571901,
            "Value": 894.3000000000001
          },
          "Online_ecom": {
            "Volume": 0,
            "Value": 0
          },
          "Others": {
            "Volume": 0,
            "Value": 0
          },
          "Cash_Withdrawal": {
            "At_ATM": {
              "Volume": 3217672,
              "Value": 11456.099999999999
            },
            "At_PoS": {
              "Volume": 0,
              "Value": 0
            }
          }
        }
      },
      "Bank_Short_Name": "CORPORATION",
      "Bank_Type": "Public Sector Banks"
    },
    {
      "Sr_No": 9,
      "Bank_Name": "DENA BANK",
      "Infrastructure": {
        "ATMs_CRMs": {
          "On_site": 683,
          "Off_site": 122
        },
        "PoS": 0,
        "Micro_ATMs": 0,
        "Bharat_QR_Codes": 0,
        "UPI_QR_Codes": 0,
        "Credit_Cards": 0,
        "Debit_Cards": 2292322
      },
      "Card_Payments_Transactions": {
        "Credit_Card": {
          "at_PoS": {
            "Volume": 0,
            "Value": 0
          },
          "Online_ecom": {
            "Volume": 0,
            "Value": 0
          },
          "Others": {
            "Volume": 0,
            "Value": 0
          },
          "Cash_Withdrawal": {
            "At_ATM": {
              "Volume": 0,
              "Value": 0
            }
          }
        },
        "Debit_Card": {
          "at_PoS": {
            "Volume": 183300,
            "Value": 250.37022199999998
          },
          "Online_ecom": {
            "Volume": 0,
            "Value": 0
          },
          "Others": {
            "Volume": 0,
            "Value": 0
          },
          "Cash_Withdrawal": {
            "At_ATM": {
              "Volume": 2392865,
              "Value": 8351.915530999999
            },
            "At_PoS": {
              "Volume": 0,
              "Value": 0
            }
          }
        }
      },
      "Bank_Short_Name": "DENA",
      "Bank_Type": "Public Sector Banks"
    },
    {
      "Sr_No": 10,
      "Bank_Name": "INDIAN BANK",
      "Infrastructure": {
        "ATMs_CRMs": {
          "On_site": 1244,
          "Off_site": 413
        },
        "PoS": 0,
        "Micro_ATMs": 0,
        "Bharat_QR_Codes": 0,
        "UPI_QR_Codes": 0,
        "Credit_Cards": 59266,
        "Debit_Cards": 10745126
      },
      "Card_Payments_Transactions": {
        "Credit_Card": {
          "at_PoS": {
            "Volume": 76659,
            "Value": 189.5
          },
          "Online_ecom": {
            "Volume": 0,
            "Value": 0
          },
          "Others": {
            "Volume": 0,
            "Value": 0
          },
          "Cash_Withdrawal": {
            "At_ATM": {
              "Volume": 2659,
              "Value": 10.4
            }
          }
        },
        "Debit_Card": {
          "at_PoS": {
            "Volume": 758738,
            "Value": 791.5999999999999
          },
          "Online_ecom": {
            "Volume": 0,
            "Value": 0
          },
          "Others": {
            "Volume": 0,
            "Value": 0
          },
          "Cash_Withdrawal": {
            "At_ATM": {
              "Volume": 11684051,
              "Value": 24004.5
            },
            "At_PoS": {
              "Volume": 0,
              "Value": 0
            }
          }
        }
      },
      "Bank_Short_Name": "INDIAN",
      "Bank_Type": "Public Sector Banks"
    },
    {
      "Sr_No": 11,
      "Bank_Name": "INDIAN OVERSEAS BANK",
      "Infrastructure": {
        "ATMs_CRMs": {
          "On_site": 1452,
          "Off_site": 821
        },
        "PoS": 471,
        "Micro_ATMs": 0,
        "Bharat_QR_Codes": 0,
        "UPI_QR_Codes": 0,
        "Credit_Cards": 46282,
        "Debit_Cards": 4909292
      },
      "Card_Payments_Transactions": {
        "Credit_Card": {
          "at_PoS": {
            "Volume": 26278,
            "Value": 65.9
          },
          "Online_ecom": {
            "Volume": 0,
            "Value": 0
          },
          "Others": {
            "Volume": 0,
            "Value": 0
          },
          "Cash_Withdrawal": {
            "At_ATM": {
              "Volume": 2901,
              "Value": 4.5
            }
          }
        },
        "Debit_Card": {
          "at_PoS": {
            "Volume": 443400,
            "Value": 895.3
          },
          "Online_ecom": {
            "Volume": 0,
            "Value": 0
          },
          "Others": {
            "Volume": 0,
            "Value": 0
          },
          "Cash_Withdrawal": {
            "At_ATM": {
              "Volume": 3632595,
              "Value": 12517.9
            },
            "At_PoS": {
              "Volume": 0,
              "Value": 0
            }
          }
        }
      },
      "Bank_Short_Name": "IOB",
      "Bank_Type": "Public Sector Banks"
    },
    {
      "Sr_No": 12,
      "Bank_Name": "ORIENTAL BANK OF COMMERCE",
      "Infrastructure": {
        "ATMs_CRMs": {
          "On_site": 1384,
          "Off_site": 371
        },
        "PoS": 1522,
        "Micro_ATMs": 0,
        "Bharat_QR_Codes": 0,
        "UPI_QR_Codes": 0,
        "Credit_Cards": 0,
        "Debit_Cards": 4679040
      },
      "Card_Payments_Transactions": {
        "Credit_Card": {
          "at_PoS": {
            "Volume": 0,
            "Value": 0
          },
          "Online_ecom": {
            "Volume": 0,
            "Value": 0
          },
          "Others": {
            "Volume": 0,
            "Value": 0
          },
          "Cash_Withdrawal": {
            "At_ATM": {
              "Volume": 0,
              "Value": 0
            }
          }
        },
        "Debit_Card": {
          "at_PoS": {
            "Volume": 210884,
            "Value": 418.974
          },
          "Online_ecom": {
            "Volume": 0,
            "Value": 0
          },
          "Others": {
            "Volume": 0,
            "Value": 0
          },
          "Cash_Withdrawal": {
            "At_ATM": {
              "Volume": 4129347,
              "Value": 16144.293192969999
            },
            "At_PoS": {
              "Volume": 0,
              "Value": 0
            }
          }
        }
      },
      "Bank_Short_Name": "OBC",
      "Bank_Type": "Public Sector Banks"
    },
    {
      "Sr_No": 13,
      "Bank_Name": "PUNJAB AND SIND BANK",
      "Infrastructure": {
        "ATMs_CRMs": {
          "On_site": 370,
          "Off_site": 70
        },
        "PoS": 0,
        "Micro_ATMs": 0,
        "Bharat_QR_Codes": 0,
        "UPI_QR_Codes": 0,
        "Credit_Cards": 0,
        "Debit_Cards": 406205
      },
      "Card_Payments_Transactions": {
        "Credit_Card": {
          "at_PoS": {
            "Volume": 0,
            "Value": 0
          },
          "Online_ecom": {
            "Volume": 0,
            "Value": 0
          },
          "Others": {
            "Volume": 0,
            "Value": 0
          },
          "Cash_Withdrawal": {
            "At_ATM": {
              "Volume": 0,
              "Value": 0
            }
          }
        },
        "Debit_Card": {
          "at_PoS": {
            "Volume": 2518,
            "Value": 6.8999999999999995
          },
          "Online_ecom": {
            "Volume": 0,
            "Value": 0
          },
          "Others": {
            "Volume": 0,
            "Value": 0
          },
          "Cash_Withdrawal": {
            "At_ATM": {
              "Volume": 275584,
              "Value": 1111.5
            },
            "At_PoS": {
              "Volume": 0,
              "Value": 0
            }
          }
        }
      },
      "Bank_Short_Name": "PSB",
      "Bank_Type": "Public Sector Banks"
    },
    {
      "Sr_No": 14,
      "Bank_Name": "PUNJAB NATIONAL BANK",
      "Infrastructure": {
        "ATMs_CRMs": {
          "On_site": 3214,
          "Off_site": 3493
        },
        "PoS": 10460,
        "Micro_ATMs": 0,
        "Bharat_QR_Codes": 0,
        "UPI_QR_Codes": 0,
        "Credit_Cards": 123397,
        "Debit_Cards": 23723688
      },
      "Card_Payments_Transactions": {
        "Credit_Card": {
          "at_PoS": {
            "Volume": 161256,
            "Value": 346.77279452999994
          },
          "Online_ecom": {
            "Volume": 0,
            "Value": 0
          },
          "Others": {
            "Volume": 0,
            "Value": 0
          },
          "Cash_Withdrawal": {
            "At_ATM": {
              "Volume": 1996,
              "Value": 8.76641471
            }
          }
        },
        "Debit_Card": {
          "at_PoS": {
            "Volume": 1668957,
            "Value": 2253.2083392400004
          },
          "Online_ecom": {
            "Volume": 0,
            "Value": 0
          },
          "Others": {
            "Volume": 0,
            "Value": 0
          },
          "Cash_Withdrawal": {
            "At_ATM": {
              "Volume": 19020339,
              "Value": 79236.86884945999
            },
            "At_PoS": {
              "Volume": 0,
              "Value": 0
            }
          }
        }
      },
      "Bank_Short_Name": "PNB",
      "Bank_Type": "Public Sector Banks"
    },
    {
      "Sr_No": 15,
      "Bank_Name": "Syndicate Bank",
      "Infrastructure": {
        "ATMs_CRMs": {
          "On_site": 1200,
          "Off_site": 200
        },
        "PoS": 944,
        "Micro_ATMs": 0,
        "Bharat_QR_Codes": 0,
        "UPI_QR_Codes": 0,
        "Credit_Cards": 68148,
        "Debit_Cards": 6012994
      },
      "Card_Payments_Transactions": {
        "Credit_Card": {
          "at_PoS": {
            "Volume": 55679,
            "Value": 118.32185842999999
          },
          "Online_ecom": {
            "Volume": 0,
            "Value": 0
          },
          "Others": {
            "Volume": 0,
            "Value": 0
          },
          "Cash_Withdrawal": {
            "At_ATM": {
              "Volume": 1588,
              "Value": 6.536052890000001
            }
          }
        },
        "Debit_Card": {
          "at_PoS": {
            "Volume": 323257,
            "Value": 549.80046105
          },
          "Online_ecom": {
            "Volume": 0,
            "Value": 0
          },
          "Others": {
            "Volume": 0,
            "Value": 0
          },
          "Cash_Withdrawal": {
            "At_ATM": {
              "Volume": 7691742,
              "Value": 19535.09554746
            },
            "At_PoS": {
              "Volume": 0,
              "Value": 0
            }
          }
        }
      },
      "Bank_Short_Name": "Syndicate",
      "Bank_Type": "Public Sector Banks"
    },
    {
      "Sr_No": 16,
      "Bank_Name": "UCO BANK",
      "Infrastructure": {
        "ATMs_CRMs": {
          "On_site": 1298,
          "Off_site": 606
        },
        "PoS": 0,
        "Micro_ATMs": 0,
        "Bharat_QR_Codes": 0,
        "UPI_QR_Codes": 0,
        "Credit_Cards": 0,
        "Debit_Cards": 3801818
      },
      "Card_Payments_Transactions": {
        "Credit_Card": {
          "at_PoS": {
            "Volume": 0,
            "Value": 0
          },
          "Online_ecom": {
            "Volume": 0,
            "Value": 0
          },
          "Others": {
            "Volume": 0,
            "Value": 0
          },
          "Cash_Withdrawal": {
            "At_ATM": {
              "Volume": 0,
              "Value": 0
            }
          }
        },
        "Debit_Card": {
          "at_PoS": {
            "Volume": 349768,
            "Value": 440.3
          },
          "Online_ecom": {
            "Volume": 0,
            "Value": 0
          },
          "Others": {
            "Volume": 0,
            "Value": 0
          },
          "Cash_Withdrawal": {
            "At_ATM": {
              "Volume": 3174334,
              "Value": 12198.5
            },
            "At_PoS": {
              "Volume": 0,
              "Value": 0
            }
          }
        }
      },
      "Bank_Short_Name": "UCO",
      "Bank_Type": "Public Sector Banks"
    },
    {
      "Sr_No": 17,
      "Bank_Name": "UNION BANK OF INDIA",
      "Infrastructure": {
        "ATMs_CRMs": {
          "On_site": 2970,
          "Off_site": 2737
        },
        "PoS": 4929,
        "Micro_ATMs": 0,
        "Bharat_QR_Codes": 0,
        "UPI_QR_Codes": 0,
        "Credit_Cards": 50575,
        "Debit_Cards": 11184840
      },
      "Card_Payments_Transactions": {
        "Credit_Card": {
          "at_PoS": {
            "Volume": 58132,
            "Value": 158.8
          },
          "Online_ecom": {
            "Volume": 0,
            "Value": 0
          },
          "Others": {
            "Volume": 0,
            "Value": 0
          },
          "Cash_Withdrawal": {
            "At_ATM": {
              "Volume": 936,
              "Value": 4.3
            }
          }
        },
        "Debit_Card": {
          "at_PoS": {
            "Volume": 739453,
            "Value": 1159.8
          },
          "Online_ecom": {
            "Volume": 0,
            "Value": 0
          },
          "Others": {
            "Volume": 0,
            "Value": 0
          },
          "Cash_Withdrawal": {
            "At_ATM": {
              "Volume": 10990240,
              "Value": 34816
            },
            "At_PoS": {
              "Volume": 0,
              "Value": 0
            }
          }
        }
      },
      "Bank_Short_Name": "UBI",
      "Bank_Type": "Public Sector Banks"
    },
    {
      "Sr_No": 18,
      "Bank_Name": "UNITED BANK OF INDIA",
      "Infrastructure": {
        "ATMs_CRMs": {
          "On_site": 560,
          "Off_site": 648
        },
        "PoS": 0,
        "Micro_ATMs": 0,
        "Bharat_QR_Codes": 0,
        "UPI_QR_Codes": 0,
        "Credit_Cards": 0,
        "Debit_Cards": 2369607
      },
      "Card_Payments_Transactions": {
        "Credit_Card": {
          "at_PoS": {
            "Volume": 0,
            "Value": 0
          },
          "Online_ecom": {
            "Volume": 0,
            "Value": 0
          },
          "Others": {
            "Volume": 0,
            "Value": 0
          },
          "Cash_Withdrawal": {
            "At_ATM": {
              "Volume": 0,
              "Value": 0
            }
          }
        },
        "Debit_Card": {
          "at_PoS": {
            "Volume": 184391,
            "Value": 316.90000000000003
          },
          "Online_ecom": {
            "Volume": 0,
            "Value": 0
          },
          "Others": {
            "Volume": 0,
            "Value": 0
          },
          "Cash_Withdrawal": {
            "At_ATM": {
              "Volume": 2592162,
              "Value": 9846.1
            },
            "At_PoS": {
              "Volume": 0,
              "Value": 0
            }
          }
        }
      },
      "Bank_Short_Name": "UNITED",
      "Bank_Type": "Public Sector Banks"
    },
    {
      "Sr_No": 19,
      "Bank_Name": "Vijaya Bank",
      "Infrastructure": {
        "ATMs_CRMs": {
          "On_site": 814,
          "Off_site": 210
        },
        "PoS": 1390,
        "Micro_ATMs": 0,
        "Bharat_QR_Codes": 0,
        "UPI_QR_Codes": 0,
        "Credit_Cards": 54914,
        "Debit_Cards": 2956779
      },
      "Card_Payments_Transactions": {
        "Credit_Card": {
          "at_PoS": {
            "Volume": 160849,
            "Value": 349.58
          },
          "Online_ecom": {
            "Volume": 0,
            "Value": 0
          },
          "Others": {
            "Volume": 0,
            "Value": 0
          },
          "Cash_Withdrawal": {
            "At_ATM": {
              "Volume": 3923,
              "Value": 21.240000000000002
            }
          }
        },
        "Debit_Card": {
          "at_PoS": {
            "Volume": 207475,
            "Value": 384.15
          },
          "Online_ecom": {
            "Volume": 0,
            "Value": 0
          },
          "Others": {
            "Volume": 0,
            "Value": 0
          },
          "Cash_Withdrawal": {
            "At_ATM": {
              "Volume": 2745579,
              "Value": 8607.859999999999
            },
            "At_PoS": {
              "Volume": 0,
              "Value": 0
            }
          }
        }
      },
      "Bank_Short_Name": "Vijaya",
      "Bank_Type": "Public Sector Banks"
    },
    {
      "Sr_No": 20,
      "Bank_Name": "STATE BANK OF INDIA",
      "Infrastructure": {
        "ATMs_CRMs": {
          "On_site": 19687,
          "Off_site": 15475
        },
        "PoS": 114406,
        "Micro_ATMs": 0,
        "Bharat_QR_Codes": 0,
        "UPI_QR_Codes": 0,
        "Credit_Cards": 2758042,
        "Debit_Cards": 127248000
      },
      "Card_Payments_Transactions": {
        "Credit_Card": {
          "at_PoS": {
            "Volume": 5439913,
            "Value": 14069.15968436
          },
          "Online_ecom": {
            "Volume": 0,
            "Value": 0
          },
          "Others": {
            "Volume": 0,
            "Value": 0
          },
          "Cash_Withdrawal": {
            "At_ATM": {
              "Volume": 42082,
              "Value": 207.32832994999998
            }
          }
        },
        "Debit_Card": {
          "at_PoS": {
            "Volume": 11071000,
            "Value": 17048.800000000003
          },
          "Online_ecom": {
            "Volume": 0,
            "Value": 0
          },
          "Others": {
            "Volume": 0,
            "Value": 0
          },
          "Cash_Withdrawal": {
            "At_ATM": {
              "Volume": 203335000,
              "Value": 584959.8
            },
            "At_PoS": {
              "Volume": 0,
              "Value": 0
            }
          }
        }
      },
      "Bank_Short_Name": "SBI",
      "Bank_Type": "Public Sector Banks"
    },
    {
      "Sr_No": 21,
      "Bank_Name": "State Bank of Bikaner & Jaipur",
      "Infrastructure": {
        "ATMs_CRMs": {
          "On_site": 721,
          "Off_site": 509
        },
        "PoS": 805,
        "Micro_ATMs": 0,
        "Bharat_QR_Codes": 0,
        "UPI_QR_Codes": 0,
        "Credit_Cards": 0,
        "Debit_Cards": 5884360
      },
      "Card_Payments_Transactions": {
        "Credit_Card": {
          "at_PoS": {
            "Volume": 0,
            "Value": 0
          },
          "Online_ecom": {
            "Volume": 0,
            "Value": 0
          },
          "Others": {
            "Volume": 0,
            "Value": 0
          },
          "Cash_Withdrawal": {
            "At_ATM": {
              "Volume": 0,
              "Value": 0
            }
          }
        },
        "Debit_Card": {
          "at_PoS": {
            "Volume": 214996,
            "Value": 269.12817878
          },
          "Online_ecom": {
            "Volume": 0,
            "Value": 0
          },
          "Others": {
            "Volume": 0,
            "Value": 0
          },
          "Cash_Withdrawal": {
            "At_ATM": {
              "Volume": 7381840,
              "Value": 22251.7796816
            },
            "At_PoS": {
              "Volume": 0,
              "Value": 0
            }
          }
        }
      },
      "Bank_Short_Name": "SBBJ",
      "Bank_Type": "Public Sector Banks"
    },
    {
      "Sr_No": 22,
      "Bank_Name": "STATE BANK OF HYDERABAD",
      "Infrastructure": {
        "ATMs_CRMs": {
          "On_site": 1307,
          "Off_site": 536
        },
        "PoS": 61,
        "Micro_ATMs": 0,
        "Bharat_QR_Codes": 0,
        "UPI_QR_Codes": 0,
        "Credit_Cards": 0,
        "Debit_Cards": 8819655
      },
      "Card_Payments_Transactions": {
        "Credit_Card": {
          "at_PoS": {
            "Volume": 0,
            "Value": 0
          },
          "Online_ecom": {
            "Volume": 0,
            "Value": 0
          },
          "Others": {
            "Volume": 0,
            "Value": 0
          },
          "Cash_Withdrawal": {
            "At_ATM": {
              "Volume": 0,
              "Value": 0
            }
          }
        },
        "Debit_Card": {
          "at_PoS": {
            "Volume": 416393,
            "Value": 794.3000000000001
          },
          "Online_ecom": {
            "Volume": 0,
            "Value": 0
          },
          "Others": {
            "Volume": 0,
            "Value": 0
          },
          "Cash_Withdrawal": {
            "At_ATM": {
              "Volume": 14183452,
              "Value": 35906.5
            },
            "At_PoS": {
              "Volume": 0,
              "Value": 0
            }
          }
        }
      },
      "Bank_Short_Name": "SBH",
      "Bank_Type": "Public Sector Banks"
    },
    {
      "Sr_No": 23,
      "Bank_Name": "STATE BANK OF MYSORE",
      "Infrastructure": {
        "ATMs_CRMs": {
          "On_site": 642,
          "Off_site": 271
        },
        "PoS": 1083,
        "Micro_ATMs": 0,
        "Bharat_QR_Codes": 0,
        "UPI_QR_Codes": 0,
        "Credit_Cards": 0,
        "Debit_Cards": 3530073
      },
      "Card_Payments_Transactions": {
        "Credit_Card": {
          "at_PoS": {
            "Volume": 0,
            "Value": 0
          },
          "Online_ecom": {
            "Volume": 0,
            "Value": 0
          },
          "Others": {
            "Volume": 0,
            "Value": 0
          },
          "Cash_Withdrawal": {
            "At_ATM": {
              "Volume": 0,
              "Value": 0
            }
          }
        },
        "Debit_Card": {
          "at_PoS": {
            "Volume": 209742,
            "Value": 448.7
          },
          "Online_ecom": {
            "Volume": 0,
            "Value": 0
          },
          "Others": {
            "Volume": 0,
            "Value": 0
          },
          "Cash_Withdrawal": {
            "At_ATM": {
              "Volume": 5397193,
              "Value": 13140
            },
            "At_PoS": {
              "Volume": 0,
              "Value": 0
            }
          }
        }
      },
      "Bank_Short_Name": "SBMysore",
      "Bank_Type": "Public Sector Banks"
    },
    {
      "Sr_No": 24,
      "Bank_Name": "State Bank of Patiala",
      "Infrastructure": {
        "ATMs_CRMs": {
          "On_site": 820,
          "Off_site": 276
        },
        "PoS": 842,
        "Micro_ATMs": 0,
        "Bharat_QR_Codes": 0,
        "UPI_QR_Codes": 0,
        "Credit_Cards": 0,
        "Debit_Cards": 4370268
      },
      "Card_Payments_Transactions": {
        "Credit_Card": {
          "at_PoS": {
            "Volume": 0,
            "Value": 0
          },
          "Online_ecom": {
            "Volume": 0,
            "Value": 0
          },
          "Others": {
            "Volume": 0,
            "Value": 0
          },
          "Cash_Withdrawal": {
            "At_ATM": {
              "Volume": 0,
              "Value": 0
            }
          }
        },
        "Debit_Card": {
          "at_PoS": {
            "Volume": 147202,
            "Value": 278.05
          },
          "Online_ecom": {
            "Volume": 0,
            "Value": 0
          },
          "Others": {
            "Volume": 0,
            "Value": 0
          },
          "Cash_Withdrawal": {
            "At_ATM": {
              "Volume": 4563638,
              "Value": 14098.67
            },
            "At_PoS": {
              "Volume": 0,
              "Value": 0
            }
          }
        }
      },
      "Bank_Short_Name": "SBP",
      "Bank_Type": "Public Sector Banks"
    },
    {
      "Sr_No": 25,
      "Bank_Name": "State Bank of Travancore",
      "Infrastructure": {
        "ATMs_CRMs": {
          "On_site": 709,
          "Off_site": 340
        },
        "PoS": 1281,
        "Micro_ATMs": 0,
        "Bharat_QR_Codes": 0,
        "UPI_QR_Codes": 0,
        "Credit_Cards": 0,
        "Debit_Cards": 7915359
      },
      "Card_Payments_Transactions": {
        "Credit_Card": {
          "at_PoS": {
            "Volume": 0,
            "Value": 0
          },
          "Online_ecom": {
            "Volume": 0,
            "Value": 0
          },
          "Others": {
            "Volume": 0,
            "Value": 0
          },
          "Cash_Withdrawal": {
            "At_ATM": {
              "Volume": 0,
              "Value": 0
            }
          }
        },
        "Debit_Card": {
          "at_PoS": {
            "Volume": 327321,
            "Value": 608.50244694
          },
          "Online_ecom": {
            "Volume": 0,
            "Value": 0
          },
          "Others": {
            "Volume": 0,
            "Value": 0
          },
          "Cash_Withdrawal": {
            "At_ATM": {
              "Volume": 7992599,
              "Value": 23640.99281951
            },
            "At_PoS": {
              "Volume": 0,
              "Value": 0
            }
          }
        }
      },
      "Bank_Short_Name": "SBT",
      "Bank_Type": "Public Sector Banks"
    },
    {
      "Sr_No": 26,
      "Bank_Name": "IDBI BANK LTD",
      "Infrastructure": {
        "ATMs_CRMs": {
          "On_site": 1026,
          "Off_site": 993
        },
        "PoS": 14417,
        "Micro_ATMs": 0,
        "Bharat_QR_Codes": 0,
        "UPI_QR_Codes": 0,
        "Credit_Cards": 0,
        "Debit_Cards": 6042406
      },
      "Card_Payments_Transactions": {
        "Credit_Card": {
          "at_PoS": {
            "Volume": 0,
            "Value": 0
          },
          "Online_ecom": {
            "Volume": 0,
            "Value": 0
          },
          "Others": {
            "Volume": 0,
            "Value": 0
          },
          "Cash_Withdrawal": {
            "At_ATM": {
              "Volume": 0,
              "Value": 0
            }
          }
        },
        "Debit_Card": {
          "at_PoS": {
            "Volume": 1054122,
            "Value": 1565.2154452464001
          },
          "Online_ecom": {
            "Volume": 0,
            "Value": 0
          },
          "Others": {
            "Volume": 0,
            "Value": 0
          },
          "Cash_Withdrawal": {
            "At_ATM": {
              "Volume": 6989358,
              "Value": 27477.77085919
            },
            "At_PoS": {
              "Volume": 0,
              "Value": 0
            }
          }
        }
      },
      "Bank_Short_Name": "IDBI",
      "Bank_Type": "Public Sector Banks"
    },
    {
      "Sr_No": 27,
      "Bank_Name": "CSB BANK LIMITED",
      "Infrastructure": {
        "ATMs_CRMs": {
          "On_site": 161,
          "Off_site": 58
        },
        "PoS": 0,
        "Micro_ATMs": 0,
        "Bharat_QR_Codes": 0,
        "UPI_QR_Codes": 0,
        "Credit_Cards": 0,
        "Debit_Cards": 543638
      },
      "Card_Payments_Transactions": {
        "Credit_Card": {
          "at_PoS": {
            "Volume": 0,
            "Value": 0
          },
          "Online_ecom": {
            "Volume": 0,
            "Value": 0
          },
          "Others": {
            "Volume": 0,
            "Value": 0
          },
          "Cash_Withdrawal": {
            "At_ATM": {
              "Volume": 0,
              "Value": 0
            }
          }
        },
        "Debit_Card": {
          "at_PoS": {
            "Volume": 14297,
            "Value": 35.30850755
          },
          "Online_ecom": {
            "Volume": 0,
            "Value": 0
          },
          "Others": {
            "Volume": 0,
            "Value": 0
          },
          "Cash_Withdrawal": {
            "At_ATM": {
              "Volume": 282631,
              "Value": 751.21454935
            },
            "At_PoS": {
              "Volume": 0,
              "Value": 0
            }
          }
        }
      },
      "Bank_Short_Name": "CSB",
      "Bank_Type": "Private Sector Banks"
    },
    {
      "Sr_No": 28,
      "Bank_Name": "CITY UNION BANK LTD",
      "Infrastructure": {
        "ATMs_CRMs": {
          "On_site": 359,
          "Off_site": 530
        },
        "PoS": 2633,
        "Micro_ATMs": 0,
        "Bharat_QR_Codes": 0,
        "UPI_QR_Codes": 0,
        "Credit_Cards": 0,
        "Debit_Cards": 1133481
      },
      "Card_Payments_Transactions": {
        "Credit_Card": {
          "at_PoS": {
            "Volume": 0,
            "Value": 0
          },
          "Online_ecom": {
            "Volume": 0,
            "Value": 0
          },
          "Others": {
            "Volume": 0,
            "Value": 0
          },
          "Cash_Withdrawal": {
            "At_ATM": {
              "Volume": 0,
              "Value": 0
            }
          }
        },
        "Debit_Card": {
          "at_PoS": {
            "Volume": 183652,
            "Value": 218.99
          },
          "Online_ecom": {
            "Volume": 0,
            "Value": 0
          },
          "Others": {
            "Volume": 0,
            "Value": 0
          },
          "Cash_Withdrawal": {
            "At_ATM": {
              "Volume": 1440145,
              "Value": 4767
            },
            "At_PoS": {
              "Volume": 0,
              "Value": 0
            }
          }
        }
      },
      "Bank_Short_Name": "CUB",
      "Bank_Type": "Private Sector Banks"
    },
    {
      "Sr_No": 29,
      "Bank_Name": "DHANALAXMI BANK LTD",
      "Infrastructure": {
        "ATMs_CRMs": {
          "On_site": 178,
          "Off_site": 218
        },
        "PoS": 0,
        "Micro_ATMs": 0,
        "Bharat_QR_Codes": 0,
        "UPI_QR_Codes": 0,
        "Credit_Cards": 3028,
        "Debit_Cards": 804601
      },
      "Card_Payments_Transactions": {
        "Credit_Card": {
          "at_PoS": {
            "Volume": 5748,
            "Value": 13.200000000000001
          },
          "Online_ecom": {
            "Volume": 0,
            "Value": 0
          },
          "Others": {
            "Volume": 0,
            "Value": 0
          },
          "Cash_Withdrawal": {
            "At_ATM": {
              "Volume": 16,
              "Value": 0.0012
            }
          }
        },
        "Debit_Card": {
          "at_PoS": {
            "Volume": 51378,
            "Value": 76.5
          },
          "Online_ecom": {
            "Volume": 0,
            "Value": 0
          },
          "Others": {
            "Volume": 0,
            "Value": 0
          },
          "Cash_Withdrawal": {
            "At_ATM": {
              "Volume": 424163,
              "Value": 1499.9
            },
            "At_PoS": {
              "Volume": 0,
              "Value": 0
            }
          }
        }
      },
      "Bank_Short_Name": "DHAN",
      "Bank_Type": "Private Sector Banks"
    },
    {
      "Sr_No": 30,
      "Bank_Name": "FEDERAL BANK LTD",
      "Infrastructure": {
        "ATMs_CRMs": {
          "On_site": 881,
          "Off_site": 420
        },
        "PoS": 8559,
        "Micro_ATMs": 0,
        "Bharat_QR_Codes": 0,
        "UPI_QR_Codes": 0,
        "Credit_Cards": 0,
        "Debit_Cards": 3562796
      },
      "Card_Payments_Transactions": {
        "Credit_Card": {
          "at_PoS": {
            "Volume": 0,
            "Value": 0
          },
          "Online_ecom": {
            "Volume": 0,
            "Value": 0
          },
          "Others": {
            "Volume": 0,
            "Value": 0
          },
          "Cash_Withdrawal": {
            "At_ATM": {
              "Volume": 0,
              "Value": 0
            }
          }
        },
        "Debit_Card": {
          "at_PoS": {
            "Volume": 384173,
            "Value": 624.5
          },
          "Online_ecom": {
            "Volume": 0,
            "Value": 0
          },
          "Others": {
            "Volume": 0,
            "Value": 0
          },
          "Cash_Withdrawal": {
            "At_ATM": {
              "Volume": 3417073,
              "Value": 14476.199999999999
            },
            "At_PoS": {
              "Volume": 0,
              "Value": 0
            }
          }
        }
      },
      "Bank_Short_Name": "FEDERAL",
      "Bank_Type": "Private Sector Banks"
    },
    {
      "Sr_No": 31,
      "Bank_Name": "ING VYSYA BANK LTD",
      "Infrastructure": {
        "ATMs_CRMs": {
          "On_site": 271,
          "Off_site": 353
        },
        "PoS": 0,
        "Micro_ATMs": 0,
        "Bharat_QR_Codes": 0,
        "UPI_QR_Codes": 0,
        "Credit_Cards": 0,
        "Debit_Cards": 1282553
      },
      "Card_Payments_Transactions": {
        "Credit_Card": {
          "at_PoS": {
            "Volume": 0,
            "Value": 0
          },
          "Online_ecom": {
            "Volume": 0,
            "Value": 0
          },
          "Others": {
            "Volume": 0,
            "Value": 0
          },
          "Cash_Withdrawal": {
            "At_ATM": {
              "Volume": 0,
              "Value": 0
            }
          }
        },
        "Debit_Card": {
          "at_PoS": {
            "Volume": 213761,
            "Value": 474.3
          },
          "Online_ecom": {
            "Volume": 0,
            "Value": 0
          },
          "Others": {
            "Volume": 0,
            "Value": 0
          },
          "Cash_Withdrawal": {
            "At_ATM": {
              "Volume": 2213146,
              "Value": 6393
            },
            "At_PoS": {
              "Volume": 0,
              "Value": 0
            }
          }
        }
      },
      "Bank_Short_Name": "ING",
      "Bank_Type": "Private Sector Banks"
    },
    {
      "Sr_No": 32,
      "Bank_Name": "JAMMU AND KASHMIR BANK",
      "Infrastructure": {
        "ATMs_CRMs": {
          "On_site": 469,
          "Off_site": 283
        },
        "PoS": 3672,
        "Micro_ATMs": 0,
        "Bharat_QR_Codes": 0,
        "UPI_QR_Codes": 0,
        "Credit_Cards": 36228,
        "Debit_Cards": 1504048
      },
      "Card_Payments_Transactions": {
        "Credit_Card": {
          "at_PoS": {
            "Volume": 51078,
            "Value": 194.56
          },
          "Online_ecom": {
            "Volume": 0,
            "Value": 0
          },
          "Others": {
            "Volume": 0,
            "Value": 0
          },
          "Cash_Withdrawal": {
            "At_ATM": {
              "Volume": 2211,
              "Value": 7.86
            }
          }
        },
        "Debit_Card": {
          "at_PoS": {
            "Volume": 45621,
            "Value": 164.54999999999998
          },
          "Online_ecom": {
            "Volume": 0,
            "Value": 0
          },
          "Others": {
            "Volume": 0,
            "Value": 0
          },
          "Cash_Withdrawal": {
            "At_ATM": {
              "Volume": 2870015,
              "Value": 13189.78
            },
            "At_PoS": {
              "Volume": 0,
              "Value": 0
            }
          }
        }
      },
      "Bank_Short_Name": "J&K",
      "Bank_Type": "Public Sector Banks"
    },
    {
      "Sr_No": 33,
      "Bank_Name": "KARNATAKA BANK LTD",
      "Infrastructure": {
        "ATMs_CRMs": {
          "On_site": 322,
          "Off_site": 270
        },
        "PoS": 2031,
        "Micro_ATMs": 0,
        "Bharat_QR_Codes": 0,
        "UPI_QR_Codes": 0,
        "Credit_Cards": 0,
        "Debit_Cards": 2059819
      },
      "Card_Payments_Transactions": {
        "Credit_Card": {
          "at_PoS": {
            "Volume": 0,
            "Value": 0
          },
          "Online_ecom": {
            "Volume": 0,
            "Value": 0
          },
          "Others": {
            "Volume": 0,
            "Value": 0
          },
          "Cash_Withdrawal": {
            "At_ATM": {
              "Volume": 0,
              "Value": 0
            }
          }
        },
        "Debit_Card": {
          "at_PoS": {
            "Volume": 226021,
            "Value": 345.09999999999997
          },
          "Online_ecom": {
            "Volume": 0,
            "Value": 0
          },
          "Others": {
            "Volume": 0,
            "Value": 0
          },
          "Cash_Withdrawal": {
            "At_ATM": {
              "Volume": 1969222,
              "Value": 6266.5
            },
            "At_PoS": {
              "Volume": 0,
              "Value": 0
            }
          }
        }
      },
      "Bank_Short_Name": "KARNATAKA",
      "Bank_Type": "Private Sector Banks"
    },
    {
      "Sr_No": 34,
      "Bank_Name": "KARUR VYSYA BANK LTD",
      "Infrastructure": {
        "ATMs_CRMs": {
          "On_site": 619,
          "Off_site": 923
        },
        "PoS": 7584,
        "Micro_ATMs": 0,
        "Bharat_QR_Codes": 0,
        "UPI_QR_Codes": 0,
        "Credit_Cards": 0,
        "Debit_Cards": 2656389
      },
      "Card_Payments_Transactions": {
        "Credit_Card": {
          "at_PoS": {
            "Volume": 0,
            "Value": 0
          },
          "Online_ecom": {
            "Volume": 0,
            "Value": 0
          },
          "Others": {
            "Volume": 0,
            "Value": 0
          },
          "Cash_Withdrawal": {
            "At_ATM": {
              "Volume": 0,
              "Value": 0
            }
          }
        },
        "Debit_Card": {
          "at_PoS": {
            "Volume": 321797,
            "Value": 426.23920051
          },
          "Online_ecom": {
            "Volume": 0,
            "Value": 0
          },
          "Others": {
            "Volume": 0,
            "Value": 0
          },
          "Cash_Withdrawal": {
            "At_ATM": {
              "Volume": 3149147,
              "Value": 12704.2114588
            },
            "At_PoS": {
              "Volume": 0,
              "Value": 0
            }
          }
        }
      },
      "Bank_Short_Name": "KVB",
      "Bank_Type": "Private Sector Banks"
    },
    {
      "Sr_No": 35,
      "Bank_Name": "Lakshmi Vilas Bank Ltd.",
      "Infrastructure": {
        "ATMs_CRMs": {
          "On_site": 193,
          "Off_site": 495
        },
        "PoS": 3405,
        "Micro_ATMs": 0,
        "Bharat_QR_Codes": 0,
        "UPI_QR_Codes": 0,
        "Credit_Cards": 0,
        "Debit_Cards": 441001
      },
      "Card_Payments_Transactions": {
        "Credit_Card": {
          "at_PoS": {
            "Volume": 0,
            "Value": 0
          },
          "Online_ecom": {
            "Volume": 0,
            "Value": 0
          },
          "Others": {
            "Volume": 0,
            "Value": 0
          },
          "Cash_Withdrawal": {
            "At_ATM": {
              "Volume": 0,
              "Value": 0
            }
          }
        },
        "Debit_Card": {
          "at_PoS": {
            "Volume": 116296,
            "Value": 313.6
          },
          "Online_ecom": {
            "Volume": 0,
            "Value": 0
          },
          "Others": {
            "Volume": 0,
            "Value": 0
          },
          "Cash_Withdrawal": {
            "At_ATM": {
              "Volume": 1342621,
              "Value": 4161.2
            },
            "At_PoS": {
              "Volume": 0,
              "Value": 0
            }
          }
        }
      },
      "Bank_Short_Name": "LVB",
      "Bank_Type": "Private Sector Banks"
    },
    {
      "Sr_No": 36,
      "Bank_Name": "RBL BANK LTD",
      "Infrastructure": {
        "ATMs_CRMs": {
          "On_site": 82,
          "Off_site": 183
        },
        "PoS": 0,
        "Micro_ATMs": 0,
        "Bharat_QR_Codes": 0,
        "UPI_QR_Codes": 0,
        "Credit_Cards": 0,
        "Debit_Cards": 75060
      },
      "Card_Payments_Transactions": {
        "Credit_Card": {
          "at_PoS": {
            "Volume": 0,
            "Value": 0
          },
          "Online_ecom": {
            "Volume": 0,
            "Value": 0
          },
          "Others": {
            "Volume": 0,
            "Value": 0
          },
          "Cash_Withdrawal": {
            "At_ATM": {
              "Volume": 0,
              "Value": 0
            }
          }
        },
        "Debit_Card": {
          "at_PoS": {
            "Volume": 12830,
            "Value": 21.41092929
          },
          "Online_ecom": {
            "Volume": 0,
            "Value": 0
          },
          "Others": {
            "Volume": 0,
            "Value": 0
          },
          "Cash_Withdrawal": {
            "At_ATM": {
              "Volume": 147620,
              "Value": 426.13280000000003
            },
            "At_PoS": {
              "Volume": 0,
              "Value": 0
            }
          }
        }
      },
      "Bank_Short_Name": "RBL",
      "Bank_Type": "Private Sector Banks"
    },
    {
      "Sr_No": 37,
      "Bank_Name": "SOUTH INDIAN BANK",
      "Infrastructure": {
        "ATMs_CRMs": {
          "On_site": 670,
          "Off_site": 228
        },
        "PoS": 333,
        "Micro_ATMs": 0,
        "Bharat_QR_Codes": 0,
        "UPI_QR_Codes": 0,
        "Credit_Cards": 0,
        "Debit_Cards": 3012462
      },
      "Card_Payments_Transactions": {
        "Credit_Card": {
          "at_PoS": {
            "Volume": 0,
            "Value": 0
          },
          "Online_ecom": {
            "Volume": 0,
            "Value": 0
          },
          "Others": {
            "Volume": 0,
            "Value": 0
          },
          "Cash_Withdrawal": {
            "At_ATM": {
              "Volume": 0,
              "Value": 0
            }
          }
        },
        "Debit_Card": {
          "at_PoS": {
            "Volume": 156506,
            "Value": 296.6
          },
          "Online_ecom": {
            "Volume": 0,
            "Value": 0
          },
          "Others": {
            "Volume": 0,
            "Value": 0
          },
          "Cash_Withdrawal": {
            "At_ATM": {
              "Volume": 1999962,
              "Value": 6654.5
            },
            "At_PoS": {
              "Volume": 0,
              "Value": 0
            }
          }
        }
      },
      "Bank_Short_Name": "SIB",
      "Bank_Type": "Private Sector Banks"
    },
    {
      "Sr_No": 38,
      "Bank_Name": "TAMILNAD MERCANTILE BANK LTD",
      "Infrastructure": {
        "ATMs_CRMs": {
          "On_site": 260,
          "Off_site": 320
        },
        "PoS": 1191,
        "Micro_ATMs": 0,
        "Bharat_QR_Codes": 0,
        "UPI_QR_Codes": 0,
        "Credit_Cards": 6162,
        "Debit_Cards": 615226
      },
      "Card_Payments_Transactions": {
        "Credit_Card": {
          "at_PoS": {
            "Volume": 5599,
            "Value": 112.83512
          },
          "Online_ecom": {
            "Volume": 0,
            "Value": 0
          },
          "Others": {
            "Volume": 0,
            "Value": 0
          },
          "Cash_Withdrawal": {
            "At_ATM": {
              "Volume": 0,
              "Value": 0
            }
          }
        },
        "Debit_Card": {
          "at_PoS": {
            "Volume": 33381,
            "Value": 86
          },
          "Online_ecom": {
            "Volume": 0,
            "Value": 0
          },
          "Others": {
            "Volume": 0,
            "Value": 0
          },
          "Cash_Withdrawal": {
            "At_ATM": {
              "Volume": 2061146,
              "Value": 7875.2
            },
            "At_PoS": {
              "Volume": 0,
              "Value": 0
            }
          }
        }
      },
      "Bank_Short_Name": "TMB",
      "Bank_Type": "Private Sector Banks"
    },
    {
      "Sr_No": 39,
      "Bank_Name": "DCB BANK LIMITED",
      "Infrastructure": {
        "ATMs_CRMs": {
          "On_site": 98,
          "Off_site": 146
        },
        "PoS": 576,
        "Micro_ATMs": 0,
        "Bharat_QR_Codes": 0,
        "UPI_QR_Codes": 0,
        "Credit_Cards": 3060,
        "Debit_Cards": 165172
      },
      "Card_Payments_Transactions": {
        "Credit_Card": {
          "at_PoS": {
            "Volume": 5054,
            "Value": 10.700000000000001
          },
          "Online_ecom": {
            "Volume": 0,
            "Value": 0
          },
          "Others": {
            "Volume": 0,
            "Value": 0
          },
          "Cash_Withdrawal": {
            "At_ATM": {
              "Volume": 419,
              "Value": 2.5
            }
          }
        },
        "Debit_Card": {
          "at_PoS": {
            "Volume": 52457,
            "Value": 95.60000000000001
          },
          "Online_ecom": {
            "Volume": 0,
            "Value": 0
          },
          "Others": {
            "Volume": 0,
            "Value": 0
          },
          "Cash_Withdrawal": {
            "At_ATM": {
              "Volume": 332195,
              "Value": 1432.1000000000001
            },
            "At_PoS": {
              "Volume": 0,
              "Value": 0
            }
          }
        }
      },
      "Bank_Short_Name": "DCB",
      "Bank_Type": "Private Sector Banks"
    },
    {
      "Sr_No": 40,
      "Bank_Name": "HDFC BANK LTD",
      "Infrastructure": {
        "ATMs_CRMs": {
          "On_site": 4651,
          "Off_site": 6694
        },
        "PoS": 223006,
        "Micro_ATMs": 0,
        "Bharat_QR_Codes": 0,
        "UPI_QR_Codes": 0,
        "Credit_Cards": 5117856,
        "Debit_Cards": 17297969
      },
      "Card_Payments_Transactions": {
        "Credit_Card": {
          "at_PoS": {
            "Volume": 13197140,
            "Value": 37382.51870085
          },
          "Online_ecom": {
            "Volume": 0,
            "Value": 0
          },
          "Others": {
            "Volume": 0,
            "Value": 0
          },
          "Cash_Withdrawal": {
            "At_ATM": {
              "Volume": 69096,
              "Value": 467.46530662
            }
          }
        },
        "Debit_Card": {
          "at_PoS": {
            "Volume": 8425986,
            "Value": 13575.35518936
          },
          "Online_ecom": {
            "Volume": 0,
            "Value": 0
          },
          "Others": {
            "Volume": 0,
            "Value": 0
          },
          "Cash_Withdrawal": {
            "At_ATM": {
              "Volume": 30426316,
              "Value": 131874.80911989
            },
            "At_PoS": {
              "Volume": 0,
              "Value": 0
            }
          }
        }
      },
      "Bank_Short_Name": "HDFC",
      "Bank_Type": "Private Sector Banks"
    },
    {
      "Sr_No": 41,
      "Bank_Name": "ICICI BANK LTD",
      "Infrastructure": {
        "ATMs_CRMs": {
          "On_site": 3692,
          "Off_site": 7483
        },
        "PoS": 228686,
        "Micro_ATMs": 0,
        "Bharat_QR_Codes": 0,
        "UPI_QR_Codes": 0,
        "Credit_Cards": 3094705,
        "Debit_Cards": 21014427
      },
      "Card_Payments_Transactions": {
        "Credit_Card": {
          "at_PoS": {
            "Volume": 5819504,
            "Value": 13245.2
          },
          "Online_ecom": {
            "Volume": 0,
            "Value": 0
          },
          "Others": {
            "Volume": 0,
            "Value": 0
          },
          "Cash_Withdrawal": {
            "At_ATM": {
              "Volume": 6633,
              "Value": 31.6
            }
          }
        },
        "Debit_Card": {
          "at_PoS": {
            "Volume": 8783452,
            "Value": 15045.029999999999
          },
          "Online_ecom": {
            "Volume": 0,
            "Value": 0
          },
          "Others": {
            "Volume": 0,
            "Value": 0
          },
          "Cash_Withdrawal": {
            "At_ATM": {
              "Volume": 31328329,
              "Value": 139124.25
            },
            "At_PoS": {
              "Volume": 0,
              "Value": 0
            }
          }
        }
      },
      "Bank_Short_Name": "ICICI",
      "Bank_Type": "Private Sector Banks"
    },
    {
      "Sr_No": 42,
      "Bank_Name": "INDUSIND BANK LTD",
      "Infrastructure": {
        "ATMs_CRMs": {
          "On_site": 479,
          "Off_site": 563
        },
        "PoS": 173,
        "Micro_ATMs": 0,
        "Bharat_QR_Codes": 0,
        "UPI_QR_Codes": 0,
        "Credit_Cards": 261871,
        "Debit_Cards": 1462578
      },
      "Card_Payments_Transactions": {
        "Credit_Card": {
          "at_PoS": {
            "Volume": 467578,
            "Value": 1755.8000000000002
          },
          "Online_ecom": {
            "Volume": 0,
            "Value": 0
          },
          "Others": {
            "Volume": 0,
            "Value": 0
          },
          "Cash_Withdrawal": {
            "At_ATM": {
              "Volume": 706,
              "Value": 4.2
            }
          }
        },
        "Debit_Card": {
          "at_PoS": {
            "Volume": 236537,
            "Value": 405.09999999999997
          },
          "Online_ecom": {
            "Volume": 0,
            "Value": 0
          },
          "Others": {
            "Volume": 0,
            "Value": 0
          },
          "Cash_Withdrawal": {
            "At_ATM": {
              "Volume": 1435071,
              "Value": 5896.799999999999
            },
            "At_PoS": {
              "Volume": 0,
              "Value": 0
            }
          }
        }
      },
      "Bank_Short_Name": "INDUSIND",
      "Bank_Type": "Private Sector Banks"
    },
    {
      "Sr_No": 43,
      "Bank_Name": "KOTAK MAHINDRA BANK LTD",
      "Infrastructure": {
        "ATMs_CRMs": {
          "On_site": 398,
          "Off_site": 631
        },
        "PoS": 0,
        "Micro_ATMs": 0,
        "Bharat_QR_Codes": 0,
        "UPI_QR_Codes": 0,
        "Credit_Cards": 392552,
        "Debit_Cards": 1068920
      },
      "Card_Payments_Transactions": {
        "Credit_Card": {
          "at_PoS": {
            "Volume": 641443,
            "Value": 2112.64712715
          },
          "Online_ecom": {
            "Volume": 0,
            "Value": 0
          },
          "Others": {
            "Volume": 0,
            "Value": 0
          },
          "Cash_Withdrawal": {
            "At_ATM": {
              "Volume": 3349,
              "Value": 22.67014172
            }
          }
        },
        "Debit_Card": {
          "at_PoS": {
            "Volume": 656264,
            "Value": 1019.59902095016
          },
          "Online_ecom": {
            "Volume": 0,
            "Value": 0
          },
          "Others": {
            "Volume": 0,
            "Value": 0
          },
          "Cash_Withdrawal": {
            "At_ATM": {
              "Volume": 2454249,
              "Value": 8958.731390950019
            },
            "At_PoS": {
              "Volume": 0,
              "Value": 0
            }
          }
        }
      },
      "Bank_Short_Name": "KOTAK",
      "Bank_Type": "Private Sector Banks"
    },
    {
      "Sr_No": 44,
      "Bank_Name": "AXIS BANK",
      "Infrastructure": {
        "ATMs_CRMs": {
          "On_site": 2430,
          "Off_site": 9596
        },
        "PoS": 240150,
        "Micro_ATMs": 0,
        "Bharat_QR_Codes": 0,
        "UPI_QR_Codes": 0,
        "Credit_Cards": 1308672,
        "Debit_Cards": 13590074
      },
      "Card_Payments_Transactions": {
        "Credit_Card": {
          "at_PoS": {
            "Volume": 2257072,
            "Value": 7354.18308703
          },
          "Online_ecom": {
            "Volume": 0,
            "Value": 0
          },
          "Others": {
            "Volume": 0,
            "Value": 0
          },
          "Cash_Withdrawal": {
            "At_ATM": {
              "Volume": 13370,
              "Value": 32.7319
            }
          }
        },
        "Debit_Card": {
          "at_PoS": {
            "Volume": 4608309,
            "Value": 7629.305982020001
          },
          "Online_ecom": {
            "Volume": 0,
            "Value": 0
          },
          "Others": {
            "Volume": 0,
            "Value": 0
          },
          "Cash_Withdrawal": {
            "At_ATM": {
              "Volume": 26774689,
              "Value": 113822.53749359999
            },
            "At_PoS": {
              "Volume": 0,
              "Value": 0
            }
          }
        }
      },
      "Bank_Short_Name": "AXIS",
      "Bank_Type": "Private Sector Banks"
    },
    {
      "Sr_No": 45,
      "Bank_Name": "YES BANK LTD",
      "Infrastructure": {
        "ATMs_CRMs": {
          "On_site": 385,
          "Off_site": 770
        },
        "PoS": 6615,
        "Micro_ATMs": 0,
        "Bharat_QR_Codes": 0,
        "UPI_QR_Codes": 0,
        "Credit_Cards": 0,
        "Debit_Cards": 536564
      },
      "Card_Payments_Transactions": {
        "Credit_Card": {
          "at_PoS": {
            "Volume": 0,
            "Value": 0
          },
          "Online_ecom": {
            "Volume": 0,
            "Value": 0
          },
          "Others": {
            "Volume": 0,
            "Value": 0
          },
          "Cash_Withdrawal": {
            "At_ATM": {
              "Volume": 0,
              "Value": 0
            }
          }
        },
        "Debit_Card": {
          "at_PoS": {
            "Volume": 246747,
            "Value": 415.20418457
          },
          "Online_ecom": {
            "Volume": 0,
            "Value": 0
          },
          "Others": {
            "Volume": 0,
            "Value": 0
          },
          "Cash_Withdrawal": {
            "At_ATM": {
              "Volume": 1093389,
              "Value": 3911.16999719
            },
            "At_PoS": {
              "Volume": 0,
              "Value": 0
            }
          }
        }
      },
      "Bank_Short_Name": "YES",
      "Bank_Type": "Private Sector Banks"
    },
    {
      "Sr_No": 46,
      "Bank_Name": "RBS (ABN AMRO)",
      "Infrastructure": {
        "ATMs_CRMs": {
          "On_site": 21,
          "Off_site": 79
        },
        "PoS": 0,
        "Micro_ATMs": 0,
        "Bharat_QR_Codes": 0,
        "UPI_QR_Codes": 0,
        "Credit_Cards": 80937,
        "Debit_Cards": 164096
      },
      "Card_Payments_Transactions": {
        "Credit_Card": {
          "at_PoS": {
            "Volume": 131990,
            "Value": 388.04559500000005
          },
          "Online_ecom": {
            "Volume": 0,
            "Value": 0
          },
          "Others": {
            "Volume": 0,
            "Value": 0
          },
          "Cash_Withdrawal": {
            "At_ATM": {
              "Volume": 581,
              "Value": 4.63428887
            }
          }
        },
        "Debit_Card": {
          "at_PoS": {
            "Volume": 88655,
            "Value": 178.4613791
          },
          "Online_ecom": {
            "Volume": 0,
            "Value": 0
          },
          "Others": {
            "Volume": 0,
            "Value": 0
          },
          "Cash_Withdrawal": {
            "At_ATM": {
              "Volume": 286372,
              "Value": 1227.44132903
            },
            "At_PoS": {
              "Volume": 0,
              "Value": 0
            }
          }
        }
      },
      "Bank_Short_Name": "RBS (ABN AMRO)",
      "Bank_Type": "Foreign Banks"
    },
    {
      "Sr_No": 47,
      "Bank_Name": "AMERICAN EXPRESS",
      "Infrastructure": {
        "ATMs_CRMs": {
          "On_site": 0,
          "Off_site": 0
        },
        "PoS": 21610,
        "Micro_ATMs": 0,
        "Bharat_QR_Codes": 0,
        "UPI_QR_Codes": 0,
        "Credit_Cards": 642336,
        "Debit_Cards": 0
      },
      "Card_Payments_Transactions": {
        "Credit_Card": {
          "at_PoS": {
            "Volume": 1717974,
            "Value": 15811.7984851789
          },
          "Online_ecom": {
            "Volume": 0,
            "Value": 0
          },
          "Others": {
            "Volume": 0,
            "Value": 0
          },
          "Cash_Withdrawal": {
            "At_ATM": {
              "Volume": 5507,
              "Value": 39.4742
            }
          }
        },
        "Debit_Card": {
          "at_PoS": {
            "Volume": 0,
            "Value": 0
          },
          "Online_ecom": {
            "Volume": 0,
            "Value": 0
          },
          "Others": {
            "Volume": 0,
            "Value": 0
          },
          "Cash_Withdrawal": {
            "At_ATM": {
              "Volume": 0,
              "Value": 0
            },
            "At_PoS": {
              "Volume": 0,
              "Value": 0
            }
          }
        }
      },
      "Bank_Short_Name": "AMEX",
      "Bank_Type": "Foreign Banks"
    },
    {
      "Sr_No": 48,
      "Bank_Name": "BARCLAYS BANK",
      "Infrastructure": {
        "ATMs_CRMs": {
          "On_site": 0,
          "Off_site": 0
        },
        "PoS": 0,
        "Micro_ATMs": 0,
        "Bharat_QR_Codes": 0,
        "UPI_QR_Codes": 0,
        "Credit_Cards": 0,
        "Debit_Cards": 4491
      },
      "Card_Payments_Transactions": {
        "Credit_Card": {
          "at_PoS": {
            "Volume": 0,
            "Value": 0
          },
          "Online_ecom": {
            "Volume": 0,
            "Value": 0
          },
          "Others": {
            "Volume": 0,
            "Value": 0
          },
          "Cash_Withdrawal": {
            "At_ATM": {
              "Volume": 0,
              "Value": 0
            }
          }
        },
        "Debit_Card": {
          "at_PoS": {
            "Volume": 332,
            "Value": 1.7844193499999998
          },
          "Online_ecom": {
            "Volume": 0,
            "Value": 0
          },
          "Others": {
            "Volume": 0,
            "Value": 0
          },
          "Cash_Withdrawal": {
            "At_ATM": {
              "Volume": 691,
              "Value": 4.2611439
            },
            "At_PoS": {
              "Volume": 0,
              "Value": 0
            }
          }
        }
      },
      "Bank_Short_Name": "BARCLAYS",
      "Bank_Type": "Foreign Banks"
    },
    {
      "Sr_No": 49,
      "Bank_Name": "CITI BANK",
      "Infrastructure": {
        "ATMs_CRMs": {
          "On_site": 56,
          "Off_site": 569
        },
        "PoS": 16672,
        "Micro_ATMs": 0,
        "Bharat_QR_Codes": 0,
        "UPI_QR_Codes": 0,
        "Credit_Cards": 2397347,
        "Debit_Cards": 1794778
      },
      "Card_Payments_Transactions": {
        "Credit_Card": {
          "at_PoS": {
            "Volume": 7732655,
            "Value": 21098.679636150002
          },
          "Online_ecom": {
            "Volume": 0,
            "Value": 0
          },
          "Others": {
            "Volume": 0,
            "Value": 0
          },
          "Cash_Withdrawal": {
            "At_ATM": {
              "Volume": 39688,
              "Value": 264.673371737538
            }
          }
        },
        "Debit_Card": {
          "at_PoS": {
            "Volume": 1903630,
            "Value": 4279.89859934
          },
          "Online_ecom": {
            "Volume": 0,
            "Value": 0
          },
          "Others": {
            "Volume": 0,
            "Value": 0
          },
          "Cash_Withdrawal": {
            "At_ATM": {
              "Volume": 3634925,
              "Value": 12869.5196075324
            },
            "At_PoS": {
              "Volume": 0,
              "Value": 0
            }
          }
        }
      },
      "Bank_Short_Name": "CITI",
      "Bank_Type": "Foreign Banks"
    },
    {
      "Sr_No": 50,
      "Bank_Name": "DEUTSCHE BANK LTD",
      "Infrastructure": {
        "ATMs_CRMs": {
          "On_site": 13,
          "Off_site": 33
        },
        "PoS": 0,
        "Micro_ATMs": 0,
        "Bharat_QR_Codes": 0,
        "UPI_QR_Codes": 0,
        "Credit_Cards": 0,
        "Debit_Cards": 76200
      },
      "Card_Payments_Transactions": {
        "Credit_Card": {
          "at_PoS": {
            "Volume": 0,
            "Value": 0
          },
          "Online_ecom": {
            "Volume": 0,
            "Value": 0
          },
          "Others": {
            "Volume": 0,
            "Value": 0
          },
          "Cash_Withdrawal": {
            "At_ATM": {
              "Volume": 0,
              "Value": 0
            }
          }
        },
        "Debit_Card": {
          "at_PoS": {
            "Volume": 89542,
            "Value": 189.827067
          },
          "Online_ecom": {
            "Volume": 0,
            "Value": 0
          },
          "Others": {
            "Volume": 0,
            "Value": 0
          },
          "Cash_Withdrawal": {
            "At_ATM": {
              "Volume": 196315,
              "Value": 810.146295
            },
            "At_PoS": {
              "Volume": 0,
              "Value": 0
            }
          }
        }
      },
      "Bank_Short_Name": "DEUTSCHE",
      "Bank_Type": "Foreign Banks"
    },
    {
      "Sr_No": 51,
      "Bank_Name": "DBS BANK",
      "Infrastructure": {
        "ATMs_CRMs": {
          "On_site": 6,
          "Off_site": 30
        },
        "PoS": 0,
        "Micro_ATMs": 0,
        "Bharat_QR_Codes": 0,
        "UPI_QR_Codes": 0,
        "Credit_Cards": 0,
        "Debit_Cards": 14963
      },
      "Card_Payments_Transactions": {
        "Credit_Card": {
          "at_PoS": {
            "Volume": 0,
            "Value": 0
          },
          "Online_ecom": {
            "Volume": 0,
            "Value": 0
          },
          "Others": {
            "Volume": 0,
            "Value": 0
          },
          "Cash_Withdrawal": {
            "At_ATM": {
              "Volume": 0,
              "Value": 0
            }
          }
        },
        "Debit_Card": {
          "at_PoS": {
            "Volume": 8261,
            "Value": 19
          },
          "Online_ecom": {
            "Volume": 0,
            "Value": 0
          },
          "Others": {
            "Volume": 0,
            "Value": 0
          },
          "Cash_Withdrawal": {
            "At_ATM": {
              "Volume": 61134,
              "Value": 167.10000000000002
            },
            "At_PoS": {
              "Volume": 0,
              "Value": 0
            }
          }
        }
      },
      "Bank_Short_Name": "DBS",
      "Bank_Type": "Foreign Banks"
    },
    {
      "Sr_No": 52,
      "Bank_Name": "HSBC",
      "Infrastructure": {
        "ATMs_CRMs": {
          "On_site": 70,
          "Off_site": 75
        },
        "PoS": 11789,
        "Micro_ATMs": 0,
        "Bharat_QR_Codes": 0,
        "UPI_QR_Codes": 0,
        "Credit_Cards": 495543,
        "Debit_Cards": 606629
      },
      "Card_Payments_Transactions": {
        "Credit_Card": {
          "at_PoS": {
            "Volume": 986617,
            "Value": 3016.65252178991
          },
          "Online_ecom": {
            "Volume": 0,
            "Value": 0
          },
          "Others": {
            "Volume": 0,
            "Value": 0
          },
          "Cash_Withdrawal": {
            "At_ATM": {
              "Volume": 3996,
              "Value": 27.99000629
            }
          }
        },
        "Debit_Card": {
          "at_PoS": {
            "Volume": 296907,
            "Value": 754.90510806
          },
          "Online_ecom": {
            "Volume": 0,
            "Value": 0
          },
          "Others": {
            "Volume": 0,
            "Value": 0
          },
          "Cash_Withdrawal": {
            "At_ATM": {
              "Volume": 485131,
              "Value": 2246.89555079
            },
            "At_PoS": {
              "Volume": 0,
              "Value": 0
            }
          }
        }
      },
      "Bank_Short_Name": "HSBC",
      "Bank_Type": "Foreign Banks"
    },
    {
      "Sr_No": 53,
      "Bank_Name": "STANDARD CHARTERED BANK",
      "Infrastructure": {
        "ATMs_CRMs": {
          "On_site": 104,
          "Off_site": 174
        },
        "PoS": 0,
        "Micro_ATMs": 0,
        "Bharat_QR_Codes": 0,
        "UPI_QR_Codes": 0,
        "Credit_Cards": 1196950,
        "Debit_Cards": 710015
      },
      "Card_Payments_Transactions": {
        "Credit_Card": {
          "at_PoS": {
            "Volume": 2252104,
            "Value": 7104.2
          },
          "Online_ecom": {
            "Volume": 0,
            "Value": 0
          },
          "Others": {
            "Volume": 0,
            "Value": 0
          },
          "Cash_Withdrawal": {
            "At_ATM": {
              "Volume": 3072,
              "Value": 13.4
            }
          }
        },
        "Debit_Card": {
          "at_PoS": {
            "Volume": 628349,
            "Value": 1152.3
          },
          "Online_ecom": {
            "Volume": 0,
            "Value": 0
          },
          "Others": {
            "Volume": 0,
            "Value": 0
          },
          "Cash_Withdrawal": {
            "At_ATM": {
              "Volume": 1359195,
              "Value": 4954.1
            },
            "At_PoS": {
              "Volume": 0,
              "Value": 0
            }
          }
        }
      },
      "Bank_Short_Name": "SCB",
      "Bank_Type": "Foreign Banks"
    }
  ],
  "total": {
    "Sr_No": 0,
    "Infrastructure": {
      "ATMs_CRMs": {
        "On_site": 69179,
        "Off_site": 67901
      },
      "PoS": 960478,
      "Micro_ATMs": 0,
      "Bharat_QR_Codes": 0,
      "UPI_QR_Codes": 0,
      "Credit_Cards": 18747076,
      "Debit_Cards": 381464280
    },
    "Card_Payments_Transactions": {
      "Credit_Card": {
        "at_PoS": {
          "Volume": 41838607,
          "Value": 126549.67199407879
        },
        "Online_ecom": {
          "Volume": 0,
          "Value": 0
        },
        "Others": {
          "Volume": 0,
          "Value": 0
        },
        "Cash_Withdrawal": {
          "At_ATM": {
            "Volume": 235633,
            "Value": 1337.1425073375378
          }
        }
      },
      "Debit_Card": {
        "at_PoS": {
          "Volume": 51623636,
          "Value": 83905.69557626656
        },
        "Online_ecom": {
          "Volume": 0,
          "Value": 0
        },
        "Others": {
          "Volume": 0,
          "Value": 0
        },
        "Cash_Withdrawal": {
          "At_ATM": {
            "Volume": 510246036,
            "Value": 1662648.4366172226
          },
          "At_PoS": {
            "Volume": 0,
            "Value": 0
          }
        }
      }
    }
  }
}